iconic_api/__init__.py
iconic_api/client.py
iconic_api/exceptions.py
iconic_api/models/__init__.py
iconic_api/models/api_requests.py
iconic_api/models/attribute.py
iconic_api/models/openapi_generated.py
iconic_api/models/stock.py
iconic_api/models/webhook.py
iconic_api/resources/__init__.py
iconic_api/resources/attribute.py
iconic_api/resources/attribute_helper.py
iconic_api/resources/attribute_set.py
iconic_api/resources/base.py
iconic_api/resources/brand.py
iconic_api/resources/category.py
iconic_api/resources/finance.py
iconic_api/resources/invoice.py
iconic_api/resources/order.py
iconic_api/resources/product.py
iconic_api/resources/product_set.py
iconic_api/resources/stock.py
iconic_api/resources/transaction.py
iconic_api/resources/webhook.py
iconic_api/throttler.py
iconic_api/utils.py
py_iconic_api-0.1.21.dist-info/LICENCE
py_iconic_api-0.1.21.dist-info/METADATA
py_iconic_api-0.1.21.dist-info/WHEEL
py_iconic_api-0.1.21.dist-info/RECORD
