Metadata-Version: 2.3
Name: py-iconic-api
Version: 0.1.21
Summary: Python package for interacting with the Iconic API
License: CC BY-NC 4.0
Keywords: iconic,theiconic,sellercenter,api,client
Author: DuneRaccoon
Author-email: benjamincsherro@hotmail.com
Requires-Python: >=3.10,<4.0
Classifier: License :: Other/Proprietary License
Classifier: Programming Language :: Python :: 3
Classifier: Programming Language :: Python :: 3.10
Classifier: Programming Language :: Python :: 3.11
Classifier: Programming Language :: Python :: 3.12
Classifier: Programming Language :: Python :: 3.13
Requires-Dist: httpx (>=0.28.1,<0.29.0)
Requires-Dist: pydantic (>=2.11.3,<3.0.0)
Project-URL: Repository, https://github.com/DuneRaccoon/py-iconic-api.git
Project-URL: Source, https://github.com/DuneRaccoon/py-iconic-api
